rbmq_channel/__init__.py
rbmq_channel/channel.py
rbmq_channel/worker.py
simple_rbmq_channel-1.1.3.dist-info/METADATA
simple_rbmq_channel-1.1.3.dist-info/WHEEL
simple_rbmq_channel-1.1.3.dist-info/top_level.txt
simple_rbmq_channel-1.1.3.dist-info/RECORD
