Metadata-Version: 2.1
Name: simple-rbmq-channel
Version: 1.1.3
Summary: Simple rabbitmq tool to publish and receive events synchronously from rabbitmq queues
Home-page: 
Author: anton emelyancev
Author-email: anttoon@me.com
Requires-Dist: pika (==1.3.0)
